{
  "Boots": "",
  "Gloves": "",
  "StackableCurrency": "",
  "AtlasUpgradeItem": "",
  "Currency": "",
  "IncubatorStackable": "",
  "DelveSocketableCurrency": "",
  "DelveStackableSocketableCurrency": "",
  "DivinationCard": "",
  "ExpeditionLogbook": "",
  "Active Skill Gem": "",
  "Support Skill Gem": "",
  "HeistBlueprint": "",
  "HeistContract": "",
  "HeistEquipmentTool": "",
  "HeistEquipmentReward": "",
  "HeistEquipmentWeapon": "",
  "HeistEquipmentUtility": "",
  "QuestItem": "",
  "VaultKey": "",
  "MapFragment": "",
  "Breachstone": "",
  "MemoryLine": "",
  "GiftBox": "",
  "Relic": "",
  "SanctumSpecialRelic": "",
  "SentinelDrone": "",
  "FishingRod": "",
  "Amulets": "",
  "Body Armours": "",
  "Helmets": "",
  "Shields": "",
  "Belts": "",
  "Hybrid Flasks": "",
  "Life Flasks": "",
  "Mana Flasks": "",
  "Utility Flasks": "",
  "Abyss Jewels": "",
  "Jewels": "",
  "Maps": "",
  "Quivers": "",
  "Rings": "",
  "Claws": "",
  "Daggers": "",
  "Rune Daggers": "",
  "One Hand Axes": "",
  "One Hand Maces": "",
  "Sceptres": "",
  "One Hand Swords": "",
  "Thrusting One Hand Swords": "",
  "Wands": "",
  "Bows": "",
  "Staffs": "",
  "Warstaffs": "",
  "Two Hand Axes": "",
  "Two Hand Maces": "",
  "Two Hand Swords": ""
}